<savedcsvimport scriptid="custimport_38_t1613115_434">
  <charencoding>windows-1252</charencoding>
  <columndelimiter>COMMA</columndelimiter>
  <datahandling>ADD</datahandling>
  <decimaldelimiter>PERIOD</decimaldelimiter>
  <ignorereadonly>T</ignorereadonly>
  <importname>Canada Invoice Upload</importname>
  <logsystemnotescustfields>F</logsystemnotescustfields>
  <multiselectdelimiter>|</multiselectdelimiter>
  <overwritemissingfields>F</overwritemissingfields>
  <overwritesublists>F</overwritesublists>
  <recordtype>INVOICE</recordtype>
  <runserversuitescript>F</runserversuitescript>
  <transactionform>STANDARDPRODUCTINVOICE</transactionform>
  <usemultithread>F</usemultithread>
  <validatemandatorycustfields>T</validatemandatorycustfields>
  <audience>
    <allemployees>F</allemployees>
    <allpartners>F</allpartners>
    <allroles>F</allroles>
    <globaledit>F</globaledit>
    <ispublic>F</ispublic>
    <roles></roles>
  </audience>
  <filemappings>
    <filemapping>
      <file>INVOICE</file>
      <primarykey>reference</primarykey>
    </filemapping>
    <filemapping>
      <file>INVOICE:ITEM</file>
      <foreignkey>reference</foreignkey>
    </filemapping>
  </filemappings>
  <recordmappings>
    <recordmapping>
      <record>INVOICE:ITEM</record>
      <fieldmappings>
        <fieldmapping>
          <field>ITEM</field>
          <columnreference>
            <column>Item</column>
            <file>INVOICE:ITEM</file>
            <type>NAME</type>
          </columnreference>
        </fieldmapping>
        <fieldmapping>
          <field>QUANTITY</field>
          <columnreference>
            <column>Qty</column>
            <file>INVOICE:ITEM</file>
            <type>NAME</type>
          </columnreference>
        </fieldmapping>
        <fieldmapping>
          <field>RATE</field>
          <columnreference>
            <column>Rate</column>
            <file>INVOICE:ITEM</file>
            <type>NAME</type>
          </columnreference>
        </fieldmapping>
        <fieldmapping>
          <field>TAXCODE</field>
          <columnreference>
            <column>Tax Code</column>
            <file>INVOICE:ITEM</file>
            <type>NAME</type>
          </columnreference>
        </fieldmapping>
      </fieldmappings>
    </recordmapping>
    <recordmapping>
      <record>INVOICE</record>
      <fieldmappings>
        <fieldmapping>
          <field>ACCOUNT</field>
          <columnreference>
            <column>account</column>
            <file>INVOICE</file>
            <type>NAME</type>
          </columnreference>
        </fieldmapping>
        <fieldmapping>
          <field>CLASS</field>
          <columnreference>
            <column>Class</column>
            <file>INVOICE</file>
            <type>NAME</type>
          </columnreference>
        </fieldmapping>
        <fieldmapping>
          <field>DEPARTMENT</field>
          <columnreference>
            <column>department</column>
            <file>INVOICE</file>
            <type>NAME</type>
          </columnreference>
        </fieldmapping>
        <fieldmapping>
          <field>ENTITY</field>
          <columnreference>
            <column>entity</column>
            <file>INVOICE</file>
            <type>INTERNAL_ID</type>
          </columnreference>
        </fieldmapping>
        <fieldmapping>
          <field>EXCHANGERATE</field>
          <columnreference>
            <column>exchange rate</column>
            <file>INVOICE</file>
            <type>NAME</type>
          </columnreference>
        </fieldmapping>
        <fieldmapping>
          <field>EXTERNALID</field>
          <columnreference>
            <column>external ID</column>
            <file>INVOICE</file>
            <type>NAME</type>
          </columnreference>
        </fieldmapping>
        <fieldmapping>
          <field>LOCATION</field>
          <columnreference>
            <column>location</column>
            <file>INVOICE</file>
            <type>NAME</type>
          </columnreference>
        </fieldmapping>
        <fieldmapping>
          <field>POSTINGPERIOD</field>
          <columnreference>
            <column>posting period</column>
            <file>INVOICE</file>
            <type>NAME</type>
          </columnreference>
        </fieldmapping>
        <fieldmapping>
          <field>TRANDATE</field>
          <columnreference>
            <column>date</column>
            <file>INVOICE</file>
            <type>NAME</type>
          </columnreference>
        </fieldmapping>
      </fieldmappings>
    </recordmapping>
  </recordmappings>
</savedcsvimport>